<?xml version="1.0" encoding="utf-8" ?>
<dwsync>
<file name="pic140.jpg" server="cis166.estrellamountain.edu" local="129990651514408992" remote="129990707770000000" Dst="0" />
<file name="pic190.jpg" server="cis166.estrellamountain.edu" local="129990649751958186" remote="129990707780000000" Dst="0" />
<file name="pic209.jpg" server="cis166.estrellamountain.edu" local="129990667373276068" remote="129990707790000000" Dst="0" />
<file name="pic230.jpg" server="cis166.estrellamountain.edu" local="129990666040349829" remote="129990707790000000" Dst="0" />
<file name="pic240.jpg" server="cis166.estrellamountain.edu" local="129990665097045875" remote="129990707800000000" Dst="0" />
<file name="pic266.jpg" server="cis166.estrellamountain.edu" local="129990664143811353" remote="129990707800000000" Dst="0" />
<file name="pic267.jpg" server="cis166.estrellamountain.edu" local="129990663813152440" remote="129990707810000000" Dst="0" />
<file name="pic293.jpg" server="cis166.estrellamountain.edu" local="129990663173285842" remote="129990707820000000" Dst="0" />
<file name="pic299.jpg" server="cis166.estrellamountain.edu" local="129990661221104184" remote="129990707820000000" Dst="0" />
<file name="pic376.jpg" server="cis166.estrellamountain.edu" local="129990659457403306" remote="129990707820000000" Dst="0" />
<file name="pic387.jpg" server="cis166.estrellamountain.edu" local="129990658174029901" remote="129990707830000000" Dst="0" />
<file name="pic392.jpg" server="cis166.estrellamountain.edu" local="129990652217989235" remote="129990707840000000" Dst="0" />
<file name="pic140.jpg" server="184.168.139.1/newportfolio/" local="130136796000000000" remote="130136796000000000" Dst="0" />
<file name="pic190.jpg" server="184.168.139.1/newportfolio/" local="130136796000000000" remote="130136796000000000" Dst="0" />
<file name="pic209.jpg" server="184.168.139.1/newportfolio/" local="130136796000000000" remote="130136796000000000" Dst="0" />
<file name="pic230.jpg" server="184.168.139.1/newportfolio/" local="130136796000000000" remote="130136796000000000" Dst="0" />
<file name="pic240.jpg" server="184.168.139.1/newportfolio/" local="130136796000000000" remote="130136796000000000" Dst="0" />
<file name="pic266.jpg" server="184.168.139.1/newportfolio/" local="130136796000000000" remote="130136796000000000" Dst="0" />
<file name="pic267.jpg" server="184.168.139.1/newportfolio/" local="130136796000000000" remote="130136796000000000" Dst="0" />
<file name="pic293.jpg" server="184.168.139.1/newportfolio/" local="130136796000000000" remote="130136796000000000" Dst="0" />
<file name="pic299.jpg" server="184.168.139.1/newportfolio/" local="130136796000000000" remote="130136796000000000" Dst="0" />
<file name="pic376.jpg" server="184.168.139.1/newportfolio/" local="130136796000000000" remote="130136796000000000" Dst="0" />
<file name="pic387.jpg" server="184.168.139.1/newportfolio/" local="130136796000000000" remote="130136796000000000" Dst="0" />
<file name="pic392.jpg" server="184.168.139.1/newportfolio/" local="130136796000000000" remote="130136796000000000" Dst="0" />
</dwsync>